pyramid_retry/__init__.py
pyramid_retry-2.1.dist-info/LICENSE.txt
pyramid_retry-2.1.dist-info/METADATA
pyramid_retry-2.1.dist-info/WHEEL
pyramid_retry-2.1.dist-info/top_level.txt
pyramid_retry-2.1.dist-info/RECORD
