Metadata-Version: 2.1
Name: pyramid-retry
Version: 2.1
Summary: An execution policy for Pyramid that supports retrying requests after certain failure exceptions.
Home-page: https://github.com/Pylons/pyramid_retry
Author: Michael Merickel
Author-email: pylons-discuss@googlegroups.com
License: UNKNOWN
Keywords: pyramid wsgi retry attempt
Platform: UNKNOWN
Classifier: Development Status :: 5 - Production/Stable
Classifier: Framework :: Pyramid
Classifier: Intended Audience :: Developers
Classifier: License :: OSI Approved :: MIT License
Classifier: Natural Language :: English
Classifier: Programming Language :: Python :: 2
Classifier: Programming Language :: Python :: 2.7
Classifier: Programming Language :: Python :: 3
Classifier: Programming Language :: Python :: 3.4
Classifier: Programming Language :: Python :: 3.5
Classifier: Programming Language :: Python :: 3.6
Classifier: Programming Language :: Python :: 3.7
Classifier: Programming Language :: Python :: Implementation :: CPython
Classifier: Programming Language :: Python :: Implementation :: PyPy
Provides-Extra: docs
Provides-Extra: testing
